ethz_snow/CITATION
ethz_snow/__init__.py
ethz_snow/constants.py
ethz_snow/operatingConditions.py
ethz_snow/snowfall.py
ethz_snow/snowflake.py
ethz_snow/snowing.py
ethz_snow/utils.py
ethz_snow/config/snowConfig_default.yaml
ethz_snow-2.0.4.dist-info/LICENSE.txt
ethz_snow-2.0.4.dist-info/METADATA
ethz_snow-2.0.4.dist-info/WHEEL
ethz_snow-2.0.4.dist-info/top_level.txt
ethz_snow-2.0.4.dist-info/RECORD
