Metadata-Version: 2.1
Name: ethz_snow
Version: 2.0.4
Summary: A Python package describing Stochastic Nucleation of Water in vials.
Home-page: https://github.com/SPL-ethz/snow
Author: Leif-Thore Deck
Author-email: deckl@ipe.mavt.ethz.ch
License: MIT
Project-URL: Documentation, https://spl-ethz.github.io/snow/
Platform: any
Classifier: Development Status :: 5 - Production/Stable
Classifier: Programming Language :: Python
Classifier: Intended Audience :: Healthcare Industry
Classifier: Intended Audience :: Manufacturing
Classifier: Intended Audience :: Science/Research
Classifier: License :: OSI Approved :: MIT License
Classifier: Topic :: Scientific/Engineering :: Chemistry
Classifier: Topic :: Scientific/Engineering :: Physics
Requires-Python: >=3.5
License-File: LICENSE.txt
Requires-Dist: numpy
Requires-Dist: scipy
Requires-Dist: matplotlib
Requires-Dist: seaborn
Requires-Dist: pandas
Requires-Dist: pyyaml >=5.1
Requires-Dist: importlib-metadata ; python_version < "3.8"
Provides-Extra: testing
Requires-Dist: setuptools ; extra == 'testing'
Requires-Dist: pytest ; extra == 'testing'
Requires-Dist: pytest-cov ; extra == 'testing'
